README.txt
setup.py
collective/__init__.py
collective.discussionintegration.plonegazette.egg-info/PKG-INFO
collective.discussionintegration.plonegazette.egg-info/SOURCES.txt
collective.discussionintegration.plonegazette.egg-info/dependency_links.txt
collective.discussionintegration.plonegazette.egg-info/entry_points.txt
collective.discussionintegration.plonegazette.egg-info/namespace_packages.txt
collective.discussionintegration.plonegazette.egg-info/not-zip-safe
collective.discussionintegration.plonegazette.egg-info/requires.txt
collective.discussionintegration.plonegazette.egg-info/top_level.txt
collective/discussionintegration/__init__.py
collective/discussionintegration/plonegazette/__init__.py
collective/discussionintegration/plonegazette/adapters.zcml
collective/discussionintegration/plonegazette/configure.zcml
collective/discussionintegration/plonegazette/interfaces.py
collective/discussionintegration/plonegazette/newsletter.py
collective/discussionintegration/plonegazette/tests.py
docs/HISTORY.txt
docs/INSTALL.txt
docs/LICENSE.GPL
docs/LICENSE.txt