Metadata-Version: 1.0
Name: collective.discussionintegration.plonegazette
Version: 1.0.0
Summary: Makes possible the creation of the PloneGazette content types if there is an installation of plone.app.discussion in your instance
Home-page: http://svn.plone.org/svn/collective/collective.discussionintegration.plonegazette
Author: RedTurtle Tecnology
Author-email: federica.delia@redturtle.net
License: GPL
Platform: UNKNOWN
Classifier: Framework :: Plone
Classifier: Programming Language :: Python
